enn_trainer/__init__.py
enn_trainer/agent.py
enn_trainer/config.py
enn_trainer/eval.py
enn_trainer/gae.py
enn_trainer/hypertuna.py
enn_trainer/load_checkpoint.py
enn_trainer/ppo.py
enn_trainer/py.typed
enn_trainer/rollout.py
enn_trainer/supervised.py
enn_trainer/tests/test_configs.py
enn_trainer/tests/test_training.py
enn_trainer/train.py
enn_trainer-0.1.16.dist-info/LICENSE-APACHE
enn_trainer-0.1.16.dist-info/LICENSE-MIT
enn_trainer-0.1.16.dist-info/METADATA
enn_trainer-0.1.16.dist-info/WHEEL
enn_trainer-0.1.16.dist-info/RECORD
