Metadata-Version: 2.1
Name: enn-trainer
Version: 0.1.16
Summary: PPO and supervised training loops compatible with entity-gym
Author: Clemens Winter
Author-email: clemenswinter1@gmail.com
Requires-Python: >=3.7.1,<3.11
Classifier: Programming Language :: Python :: 3
Classifier: Programming Language :: Python :: 3.8
Classifier: Programming Language :: Python :: 3.9
Classifier: Programming Language :: Python :: 3.10
Requires-Dist: click (>=8.0.4,<9.0.0)
Requires-Dist: entity-gym (>=0.1.10,<0.2.0)
Requires-Dist: hyperstate (>=0.4.3,<0.5.0)
Requires-Dist: moviepy (>=1.0.3,<2.0.0)
Requires-Dist: msgpack (>=1.0.3,<2.0.0)
Requires-Dist: msgpack-numpy (>=0.4.7,<0.5.0)
Requires-Dist: numpy (>=1.21.4,<2.0.0)
Requires-Dist: optuna (>=2.10.0,<3.0.0)
Requires-Dist: ragged-buffer (>=0.4.8,<0.5.0)
Requires-Dist: rogue-net (>=0.1.9,<0.2.0)
Requires-Dist: tensorboard (>=2.7.0,<3.0.0)
Requires-Dist: tqdm (>=4.62.3,<5.0.0)
Requires-Dist: wandb (>=0.12.7,<0.13.0)
